{
  "name": "Function",
  "base": "PersistedModel",
  "idInjection": false,
  "options": {
    "validateUpsert": true
  },
  "properties": {
    "id": {
      "type": "string",
      "id": true,
      "required": false,
      "defaultFn": "uuidv4"
    },
    "name": {
      "type": "string",
      "required": true
    },
    "contextPath": {
      "type": "string"
    },
    "itemOrder": {
      "type": "number",
      "required": true,
      "default": 0
    },
    "base": {
      "type": "string",
      "default": "Model"
    },
    "plural": {
      "type": "string"
    },
    "readOnly": {
      "type": "boolean",
      "default": false
    },
    "public": {
      "type": "boolean",
      "default": false
    },
    "strict": {
      "type": "boolean",
      "default": false
    },
    "privateModelProperties": {
      "type": "array",
      "items": {
        "type": "object",
        "properties": {
          "id": {
            "type": "string"
          },
          "propertyKey": {
            "type": "string"
          },
          "propertyValue": {
            "type": "string"
          },
          "propertyType": {
            "type": "string"
          },
          "propertyIsRequired": {
            "type": "boolean"
          },
          "propertyIsIndex": {
            "type": "boolean"
          },
          "propertyNotes": {
            "type": "string"
          }
        },
        "required": ["id"]
      }
    },
    "privateModelRelations": {
      "type": "array",
      "items": {
        "type": "object",
        "properties": {
          "id": {
            "type": "string"
          },
          "relationType": {
            "type": "string"
          },
          "relationForeignKey": {
            "type": "string"
          },
          "relationModel": {
            "type": "string"
          }
        },
        "required": ["id"],
        "additionalProperties": false
      }
    }
  },
  "validations": [],
  "relations": {},
  "acls": [],
  "methods": {}
}
